get_reads_taxonomy/__init__.py
get_reads_taxonomy/__main__.py
get_reads_taxonomy/_version.py
get_reads_taxonomy/defaults.py
get_reads_taxonomy/extract.py
get_reads_taxonomy/lib.py
get_reads_taxonomy/utils.py
get_reads_taxonomy-0.0.3.dist-info/LICENSE
get_reads_taxonomy-0.0.3.dist-info/METADATA
get_reads_taxonomy-0.0.3.dist-info/WHEEL
get_reads_taxonomy-0.0.3.dist-info/entry_points.txt
get_reads_taxonomy-0.0.3.dist-info/top_level.txt
get_reads_taxonomy-0.0.3.dist-info/RECORD
