Metadata-Version: 2.1
Name: get-reads-taxonomy
Version: 0.0.3
Summary: A simple tool to extract reads from a certain taxa from BAM files
Home-page: https://github.com/genomewalker/get-reads-taxonomy
Author: Antonio Fernandez-Guerra
Author-email: antonio@metagenomics.eu
License: MIT
Keywords: get-reads-taxonomy,GTDB
Platform: UNKNOWN
Classifier: Programming Language :: Python :: 3.8
Classifier: Programming Language :: Python :: 3.9
License-File: LICENSE
Requires-Dist: pandas >=1.4.2
Requires-Dist: tqdm >=4.64.1
Requires-Dist: pysam >=0.17.0
Requires-Dist: numpy >=1.21.2
Requires-Dist: biopython >=1.79
